[{"compra_data": "23-03-2015", "compra_pre\u00e7o": 13.124740600585938, "venda_data": "27-03-2015", "venda_pre\u00e7o": 12.256904602050781, "resultado": "-6.61%", "no_preg\u00f5es": 4}, {"compra_data": "02-04-2015", "compra_pre\u00e7o": 13.211498260498047, "venda_data": "21-05-2015", "venda_pre\u00e7o": 12.801762580871582, "resultado": "-3.10%", "no_preg\u00f5es": 32}, {"compra_data": "16-07-2015", "compra_pre\u00e7o": 12.489494323730469, "venda_data": "21-07-2015", "venda_pre\u00e7o": 12.057329177856445, "resultado": "-3.46%", "no_preg\u00f5es": 3}, {"compra_data": "09-10-2015", "compra_pre\u00e7o": 10.390631675720215, "venda_data": "13-10-2015", "venda_pre\u00e7o": 9.823240280151367, "resultado": "-5.46%", "no_preg\u00f5es": 1}, {"compra_data": "19-11-2015", "compra_pre\u00e7o": 10.143004417419434, "venda_data": "30-11-2015", "venda_pre\u00e7o": 9.154705047607422, "resultado": "-9.74%", "no_preg\u00f5es": 6}, {"compra_data": "10-02-2016", "compra_pre\u00e7o": 8.910152435302734, "venda_data": "23-05-2016", "venda_pre\u00e7o": 12.159000396728516, "resultado": "36.46%", "no_preg\u00f5es": 71}, {"compra_data": "23-06-2016", "compra_pre\u00e7o": 12.764277458190918, "venda_data": "16-09-2016", "venda_pre\u00e7o": 14.103789329528809, "resultado": "10.49%", "no_preg\u00f5es": 60}, {"compra_data": "22-09-2016", "compra_pre\u00e7o": 14.897101402282715, "venda_data": "14-11-2016", "venda_pre\u00e7o": 15.001364707946777, "resultado": "0.70%", "no_preg\u00f5es": 35}, {"compra_data": "04-01-2017", "compra_pre\u00e7o": 15.4426908493042, "venda_data": "17-03-2017", "venda_pre\u00e7o": 16.345735549926758, "resultado": "5.85%", "no_preg\u00f5es": 49}, {"compra_data": "03-04-2017", "compra_pre\u00e7o": 16.874696731567383, "venda_data": "06-04-2017", "venda_pre\u00e7o": 16.47893714904785, "resultado": "-2.35%", "no_preg\u00f5es": 3}, {"compra_data": "27-04-2017", "compra_pre\u00e7o": 17.37656021118164, "venda_data": "22-05-2017", "venda_pre\u00e7o": 15.395770072937012, "resultado": "-11.40%", "no_preg\u00f5es": 16}, {"compra_data": "04-07-2017", "compra_pre\u00e7o": 16.23482322692871, "venda_data": "31-10-2017", "venda_pre\u00e7o": 19.98227882385254, "resultado": "23.08%", "no_preg\u00f5es": 85}, {"compra_data": "25-12-2017", "compra_pre\u00e7o": 19.651296615600586, "venda_data": "19-03-2018", "venda_pre\u00e7o": 22.350799560546875, "resultado": "13.74%", "no_preg\u00f5es": 56}, {"compra_data": "29-03-2018", "compra_pre\u00e7o": 23.331314086914062, "venda_data": "10-04-2018", "venda_pre\u00e7o": 22.485151290893555, "resultado": "-3.63%", "no_preg\u00f5es": 7}, {"compra_data": "11-04-2018", "compra_pre\u00e7o": 23.011690139770508, "venda_data": "12-04-2018", "venda_pre\u00e7o": 22.59565544128418, "resultado": "-1.81%", "no_preg\u00f5es": 1}, {"compra_data": "13-07-2018", "compra_pre\u00e7o": 19.05193328857422, "venda_data": "20-08-2018", "venda_pre\u00e7o": 18.88550567626953, "resultado": "-0.87%", "no_preg\u00f5es": 26}, {"compra_data": "02-10-2018", "compra_pre\u00e7o": 19.69646644592285, "venda_data": "22-03-2019", "venda_pre\u00e7o": 27.633987426757812, "resultado": "40.30%", "no_preg\u00f5es": 111}, {"compra_data": "29-05-2019", "compra_pre\u00e7o": 29.29904556274414, "venda_data": "29-07-2019", "venda_pre\u00e7o": 29.24248504638672, "resultado": "-0.19%", "no_preg\u00f5es": 41}, {"compra_data": "23-09-2019", "compra_pre\u00e7o": 27.73418426513672, "venda_data": "02-10-2019", "venda_pre\u00e7o": 26.047130584716797, "resultado": "-6.08%", "no_preg\u00f5es": 7}, {"compra_data": "15-10-2019", "compra_pre\u00e7o": 28.169784545898438, "venda_data": "18-11-2019", "venda_pre\u00e7o": 27.60253143310547, "resultado": "-2.01%", "no_preg\u00f5es": 23}, {"compra_data": "06-12-2019", "compra_pre\u00e7o": 28.60033416748047, "venda_data": "22-01-2020", "venda_pre\u00e7o": 29.024127960205078, "resultado": "1.48%", "no_preg\u00f5es": 29}, {"compra_data": "03-06-2020", "compra_pre\u00e7o": 18.690521240234375, "venda_data": "11-08-2020", "venda_pre\u00e7o": 18.94877815246582, "resultado": "1.38%", "no_preg\u00f5es": 48}, {"compra_data": "19-10-2020", "compra_pre\u00e7o": 17.906890869140625, "venda_data": "26-01-2021", "venda_pre\u00e7o": 21.578943252563477, "resultado": "20.51%", "no_preg\u00f5es": 64}]