[{"compra_data": "30-01-2015", "compra_pre\u00e7o": 8.124466896057129, "venda_data": "23-02-2015", "venda_pre\u00e7o": 8.76425552368164, "resultado": "7.87%", "no_preg\u00f5es": 14}, {"compra_data": "24-02-2015", "compra_pre\u00e7o": 8.843133926391602, "venda_data": "27-02-2015", "venda_pre\u00e7o": 8.886956214904785, "resultado": "0.50%", "no_preg\u00f5es": 3}, {"compra_data": "04-03-2015", "compra_pre\u00e7o": 9.167413711547852, "venda_data": "16-03-2015", "venda_pre\u00e7o": 9.421574592590332, "resultado": "2.77%", "no_preg\u00f5es": 8}, {"compra_data": "17-03-2015", "compra_pre\u00e7o": 9.783267974853516, "venda_data": "24-03-2015", "venda_pre\u00e7o": 9.624472618103027, "resultado": "-1.62%", "no_preg\u00f5es": 5}, {"compra_data": "25-03-2015", "compra_pre\u00e7o": 9.80972957611084, "venda_data": "26-03-2015", "venda_pre\u00e7o": 9.54507827758789, "resultado": "-2.70%", "no_preg\u00f5es": 1}, {"compra_data": "15-04-2015", "compra_pre\u00e7o": 8.821698188781738, "venda_data": "16-04-2015", "venda_pre\u00e7o": 8.512941360473633, "resultado": "-3.50%", "no_preg\u00f5es": 1}, {"compra_data": "22-04-2015", "compra_pre\u00e7o": 8.601156234741211, "venda_data": "06-05-2015", "venda_pre\u00e7o": 9.024598121643066, "resultado": "4.92%", "no_preg\u00f5es": 9}, {"compra_data": "08-05-2015", "compra_pre\u00e7o": 9.130459785461426, "venda_data": "12-05-2015", "venda_pre\u00e7o": 8.927560806274414, "resultado": "-2.22%", "no_preg\u00f5es": 2}, {"compra_data": "02-06-2015", "compra_pre\u00e7o": 8.02561092376709, "venda_data": "03-06-2015", "venda_pre\u00e7o": 7.8924407958984375, "resultado": "-1.66%", "no_preg\u00f5es": 1}, {"compra_data": "13-07-2015", "compra_pre\u00e7o": 6.250033378601074, "venda_data": "14-07-2015", "venda_pre\u00e7o": 5.779505729675293, "resultado": "-7.53%", "no_preg\u00f5es": 1}, {"compra_data": "03-08-2015", "compra_pre\u00e7o": 5.229074954986572, "venda_data": "11-08-2015", "venda_pre\u00e7o": 5.300098419189453, "resultado": "1.36%", "no_preg\u00f5es": 6}, {"compra_data": "27-08-2015", "compra_pre\u00e7o": 4.898031711578369, "venda_data": "18-09-2015", "venda_pre\u00e7o": 5.732309818267822, "resultado": "17.03%", "no_preg\u00f5es": 15}, {"compra_data": "05-10-2015", "compra_pre\u00e7o": 5.346569538116455, "venda_data": "16-10-2015", "venda_pre\u00e7o": 5.561866283416748, "resultado": "4.03%", "no_preg\u00f5es": 8}, {"compra_data": "03-11-2015", "compra_pre\u00e7o": 5.2748026847839355, "venda_data": "04-11-2015", "venda_pre\u00e7o": 5.095387935638428, "resultado": "-3.40%", "no_preg\u00f5es": 1}, {"compra_data": "05-11-2015", "compra_pre\u00e7o": 5.194066047668457, "venda_data": "09-11-2015", "venda_pre\u00e7o": 4.987739086151123, "resultado": "-3.97%", "no_preg\u00f5es": 2}, {"compra_data": "19-11-2015", "compra_pre\u00e7o": 5.276882171630859, "venda_data": "01-12-2015", "venda_pre\u00e7o": 5.34916877746582, "resultado": "1.37%", "no_preg\u00f5es": 7}, {"compra_data": "18-12-2015", "compra_pre\u00e7o": 4.454628944396973, "venda_data": "21-12-2015", "venda_pre\u00e7o": 4.201627254486084, "resultado": "-5.68%", "no_preg\u00f5es": 1}, {"compra_data": "28-01-2016", "compra_pre\u00e7o": 3.081193447113037, "venda_data": "11-02-2016", "venda_pre\u00e7o": 3.361302375793457, "resultado": "9.09%", "no_preg\u00f5es": 8}, {"compra_data": "16-02-2016", "compra_pre\u00e7o": 3.7046608924865723, "venda_data": "23-02-2016", "venda_pre\u00e7o": 3.5149097442626953, "resultado": "-5.12%", "no_preg\u00f5es": 5}, {"compra_data": "03-03-2016", "compra_pre\u00e7o": 3.6504459381103516, "venda_data": "15-03-2016", "venda_pre\u00e7o": 4.291985034942627, "resultado": "17.57%", "no_preg\u00f5es": 8}, {"compra_data": "16-03-2016", "compra_pre\u00e7o": 4.517879009246826, "venda_data": "06-04-2016", "venda_pre\u00e7o": 5.665421485900879, "resultado": "25.40%", "no_preg\u00f5es": 14}, {"compra_data": "08-04-2016", "compra_pre\u00e7o": 6.153351783752441, "venda_data": "22-04-2016", "venda_pre\u00e7o": 7.011748790740967, "resultado": "13.95%", "no_preg\u00f5es": 9}, {"compra_data": "27-04-2016", "compra_pre\u00e7o": 7.3099284172058105, "venda_data": "28-04-2016", "venda_pre\u00e7o": 7.011748790740967, "resultado": "-4.08%", "no_preg\u00f5es": 1}, {"compra_data": "29-04-2016", "compra_pre\u00e7o": 7.056927680969238, "venda_data": "02-05-2016", "venda_pre\u00e7o": 6.858139991760254, "resultado": "-2.82%", "no_preg\u00f5es": 1}, {"compra_data": "11-05-2016", "compra_pre\u00e7o": 6.623210430145264, "venda_data": "12-05-2016", "venda_pre\u00e7o": 6.370208263397217, "resultado": "-3.82%", "no_preg\u00f5es": 1}, {"compra_data": "02-06-2016", "compra_pre\u00e7o": 5.19556188583374, "venda_data": "10-06-2016", "venda_pre\u00e7o": 5.2949538230896, "resultado": "1.91%", "no_preg\u00f5es": 6}, {"compra_data": "23-06-2016", "compra_pre\u00e7o": 5.647349834442139, "venda_data": "24-06-2016", "venda_pre\u00e7o": 5.2949538230896, "resultado": "-6.24%", "no_preg\u00f5es": 1}, {"compra_data": "30-06-2016", "compra_pre\u00e7o": 5.322061538696289, "venda_data": "24-08-2016", "venda_pre\u00e7o": 8.257192611694336, "resultado": "55.15%", "no_preg\u00f5es": 39}, {"compra_data": "02-09-2016", "compra_pre\u00e7o": 8.583492279052734, "venda_data": "09-09-2016", "venda_pre\u00e7o": 8.402215003967285, "resultado": "-2.11%", "no_preg\u00f5es": 4}, {"compra_data": "12-09-2016", "compra_pre\u00e7o": 8.592556953430176, "venda_data": "13-09-2016", "venda_pre\u00e7o": 7.8402533531188965, "resultado": "-8.76%", "no_preg\u00f5es": 1}, {"compra_data": "21-09-2016", "compra_pre\u00e7o": 7.949019908905029, "venda_data": "01-11-2016", "venda_pre\u00e7o": 9.571455955505371, "resultado": "20.41%", "no_preg\u00f5es": 28}, {"compra_data": "07-11-2016", "compra_pre\u00e7o": 10.069968223571777, "venda_data": "30-11-2016", "venda_pre\u00e7o": 12.299725532531738, "resultado": "22.14%", "no_preg\u00f5es": 16}, {"compra_data": "07-12-2016", "compra_pre\u00e7o": 12.454033851623535, "venda_data": "09-12-2016", "venda_pre\u00e7o": 11.68246841430664, "resultado": "-6.20%", "no_preg\u00f5es": 2}, {"compra_data": "27-12-2016", "compra_pre\u00e7o": 9.966861724853516, "venda_data": "19-01-2017", "venda_pre\u00e7o": 10.983518600463867, "resultado": "10.20%", "no_preg\u00f5es": 16}, {"compra_data": "01-02-2017", "compra_pre\u00e7o": 11.27398681640625, "venda_data": "06-02-2017", "venda_pre\u00e7o": 11.255834579467773, "resultado": "-0.16%", "no_preg\u00f5es": 3}, {"compra_data": "09-02-2017", "compra_pre\u00e7o": 11.346609115600586, "venda_data": "22-02-2017", "venda_pre\u00e7o": 11.900321960449219, "resultado": "4.88%", "no_preg\u00f5es": 9}, {"compra_data": "01-03-2017", "compra_pre\u00e7o": 12.072790145874023, "venda_data": "02-03-2017", "venda_pre\u00e7o": 11.864011764526367, "resultado": "-1.73%", "no_preg\u00f5es": 1}, {"compra_data": "03-03-2017", "compra_pre\u00e7o": 12.118178367614746, "venda_data": "06-03-2017", "venda_pre\u00e7o": 11.900321960449219, "resultado": "-1.80%", "no_preg\u00f5es": 1}, {"compra_data": "15-03-2017", "compra_pre\u00e7o": 11.864011764526367, "venda_data": "17-03-2017", "venda_pre\u00e7o": 11.201370239257812, "resultado": "-5.59%", "no_preg\u00f5es": 2}, {"compra_data": "20-03-2017", "compra_pre\u00e7o": 11.473689079284668, "venda_data": "21-03-2017", "venda_pre\u00e7o": 10.656734466552734, "resultado": "-7.12%", "no_preg\u00f5es": 1}, {"compra_data": "24-04-2017", "compra_pre\u00e7o": 8.768658638000488, "venda_data": "03-05-2017", "venda_pre\u00e7o": 8.677886962890625, "resultado": "-1.04%", "no_preg\u00f5es": 6}, {"compra_data": "10-05-2017", "compra_pre\u00e7o": 8.904817581176758, "venda_data": "18-05-2017", "venda_pre\u00e7o": 8.1695556640625, "resultado": "-8.26%", "no_preg\u00f5es": 6}, {"compra_data": "23-05-2017", "compra_pre\u00e7o": 8.932049751281738, "venda_data": "24-05-2017", "venda_pre\u00e7o": 8.768658638000488, "resultado": "-1.83%", "no_preg\u00f5es": 1}, {"compra_data": "30-05-2017", "compra_pre\u00e7o": 9.022822380065918, "venda_data": "31-05-2017", "venda_pre\u00e7o": 8.659730911254883, "resultado": "-4.02%", "no_preg\u00f5es": 1}, {"compra_data": "08-06-2017", "compra_pre\u00e7o": 8.686962127685547, "venda_data": "13-06-2017", "venda_pre\u00e7o": 8.605267524719238, "resultado": "-0.94%", "no_preg\u00f5es": 3}, {"compra_data": "22-06-2017", "compra_pre\u00e7o": 8.496338844299316, "venda_data": "18-07-2017", "venda_pre\u00e7o": 9.830700874328613, "resultado": "15.71%", "no_preg\u00f5es": 18}, {"compra_data": "19-07-2017", "compra_pre\u00e7o": 10.039478302001953, "venda_data": "20-07-2017", "venda_pre\u00e7o": 9.867009162902832, "resultado": "-1.72%", "no_preg\u00f5es": 1}, {"compra_data": "24-07-2017", "compra_pre\u00e7o": 9.948704719543457, "venda_data": "26-07-2017", "venda_pre\u00e7o": 9.576537132263184, "resultado": "-3.74%", "no_preg\u00f5es": 2}, {"compra_data": "02-08-2017", "compra_pre\u00e7o": 9.867009162902832, "venda_data": "14-08-2017", "venda_pre\u00e7o": 10.166558265686035, "resultado": "3.04%", "no_preg\u00f5es": 8}, {"compra_data": "22-08-2017", "compra_pre\u00e7o": 10.33049488067627, "venda_data": "08-09-2017", "venda_pre\u00e7o": 11.112556457519531, "resultado": "7.57%", "no_preg\u00f5es": 13}, {"compra_data": "03-10-2017", "compra_pre\u00e7o": 10.366869926452637, "venda_data": "05-10-2017", "venda_pre\u00e7o": 10.075868606567383, "resultado": "-2.81%", "no_preg\u00f5es": 2}, {"compra_data": "10-10-2017", "compra_pre\u00e7o": 10.1395263671875, "venda_data": "11-10-2017", "venda_pre\u00e7o": 10.021307945251465, "resultado": "-1.17%", "no_preg\u00f5es": 1}, {"compra_data": "13-10-2017", "compra_pre\u00e7o": 10.403244972229004, "venda_data": "27-10-2017", "venda_pre\u00e7o": 10.530555725097656, "resultado": "1.22%", "no_preg\u00f5es": 10}, {"compra_data": "17-11-2017", "compra_pre\u00e7o": 9.584806442260742, "venda_data": "19-01-2018", "venda_pre\u00e7o": 12.913533210754395, "resultado": "34.73%", "no_preg\u00f5es": 44}, {"compra_data": "26-01-2018", "compra_pre\u00e7o": 13.624872207641602, "venda_data": "05-02-2018", "venda_pre\u00e7o": 12.53050708770752, "resultado": "-8.03%", "no_preg\u00f5es": 6}, {"compra_data": "06-02-2018", "compra_pre\u00e7o": 13.287440299987793, "venda_data": "07-02-2018", "venda_pre\u00e7o": 12.82233715057373, "resultado": "-3.50%", "no_preg\u00f5es": 1}, {"compra_data": "15-02-2018", "compra_pre\u00e7o": 13.679590225219727, "venda_data": "06-03-2018", "venda_pre\u00e7o": 14.883398056030273, "resultado": "8.80%", "no_preg\u00f5es": 13}, {"compra_data": "21-03-2018", "compra_pre\u00e7o": 14.600480079650879, "venda_data": "22-03-2018", "venda_pre\u00e7o": 14.034001350402832, "resultado": "-3.88%", "no_preg\u00f5es": 1}, {"compra_data": "29-03-2018", "compra_pre\u00e7o": 14.16191577911377, "venda_data": "24-04-2018", "venda_pre\u00e7o": 15.31314468383789, "resultado": "8.13%", "no_preg\u00f5es": 17}, {"compra_data": "26-04-2018", "compra_pre\u00e7o": 15.550699234008789, "venda_data": "27-04-2018", "venda_pre\u00e7o": 15.240047454833984, "resultado": "-2.00%", "no_preg\u00f5es": 1}, {"compra_data": "04-05-2018", "compra_pre\u00e7o": 15.386236190795898, "venda_data": "07-05-2018", "venda_pre\u00e7o": 14.947675704956055, "resultado": "-2.85%", "no_preg\u00f5es": 1}, {"compra_data": "09-05-2018", "compra_pre\u00e7o": 15.861347198486328, "venda_data": "21-05-2018", "venda_pre\u00e7o": 15.687747955322266, "resultado": "-1.09%", "no_preg\u00f5es": 8}, {"compra_data": "04-06-2018", "compra_pre\u00e7o": 14.567852020263672, "venda_data": "07-06-2018", "venda_pre\u00e7o": 13.62236499786377, "resultado": "-6.49%", "no_preg\u00f5es": 3}, {"compra_data": "20-06-2018", "compra_pre\u00e7o": 13.530569076538086, "venda_data": "21-06-2018", "venda_pre\u00e7o": 12.842107772827148, "resultado": "-5.09%", "no_preg\u00f5es": 1}, {"compra_data": "03-07-2018", "compra_pre\u00e7o": 13.117491722106934, "venda_data": "26-07-2018", "venda_pre\u00e7o": 14.925851821899414, "resultado": "13.79%", "no_preg\u00f5es": 16}, {"compra_data": "27-07-2018", "compra_pre\u00e7o": 15.458260536193848, "venda_data": "01-08-2018", "venda_pre\u00e7o": 15.054363250732422, "resultado": "-2.61%", "no_preg\u00f5es": 3}, {"compra_data": "02-08-2018", "compra_pre\u00e7o": 15.274672508239746, "venda_data": "07-08-2018", "venda_pre\u00e7o": 15.311388969421387, "resultado": "0.24%", "no_preg\u00f5es": 3}, {"compra_data": "08-08-2018", "compra_pre\u00e7o": 15.788724899291992, "venda_data": "09-08-2018", "venda_pre\u00e7o": 15.412365913391113, "resultado": "-2.38%", "no_preg\u00f5es": 1}, {"compra_data": "20-08-2018", "compra_pre\u00e7o": 14.87995433807373, "venda_data": "21-08-2018", "venda_pre\u00e7o": 14.64128589630127, "resultado": "-1.60%", "no_preg\u00f5es": 1}, {"compra_data": "22-08-2018", "compra_pre\u00e7o": 15.020980834960938, "venda_data": "30-08-2018", "venda_pre\u00e7o": 14.743156433105469, "resultado": "-1.85%", "no_preg\u00f5es": 6}, {"compra_data": "31-08-2018", "compra_pre\u00e7o": 14.854288101196289, "venda_data": "03-09-2018", "venda_pre\u00e7o": 14.678330421447754, "resultado": "-1.18%", "no_preg\u00f5es": 1}, {"compra_data": "17-09-2018", "compra_pre\u00e7o": 14.474594116210938, "venda_data": "01-10-2018", "venda_pre\u00e7o": 15.446974754333496, "resultado": "6.72%", "no_preg\u00f5es": 10}, {"compra_data": "16-10-2018", "compra_pre\u00e7o": 15.002459526062012, "venda_data": "18-10-2018", "venda_pre\u00e7o": 14.344942092895508, "resultado": "-4.38%", "no_preg\u00f5es": 2}, {"compra_data": "22-10-2018", "compra_pre\u00e7o": 14.622766494750977, "venda_data": "23-10-2018", "venda_pre\u00e7o": 14.52089786529541, "resultado": "-0.70%", "no_preg\u00f5es": 1}, {"compra_data": "26-10-2018", "compra_pre\u00e7o": 14.622766494750977, "venda_data": "08-11-2018", "venda_pre\u00e7o": 14.891329765319824, "resultado": "1.84%", "no_preg\u00f5es": 8}, {"compra_data": "16-11-2018", "compra_pre\u00e7o": 15.030240058898926, "venda_data": "21-11-2018", "venda_pre\u00e7o": 14.215292930603027, "resultado": "-5.42%", "no_preg\u00f5es": 2}, {"compra_data": "30-11-2018", "compra_pre\u00e7o": 14.458127975463867, "venda_data": "10-12-2018", "venda_pre\u00e7o": 14.31803035736084, "resultado": "-0.97%", "no_preg\u00f5es": 6}, {"compra_data": "02-01-2019", "compra_pre\u00e7o": 14.196611404418945, "venda_data": "11-01-2019", "venda_pre\u00e7o": 14.215292930603027, "resultado": "0.13%", "no_preg\u00f5es": 7}, {"compra_data": "18-01-2019", "compra_pre\u00e7o": 14.467467308044434, "venda_data": "31-01-2019", "venda_pre\u00e7o": 14.616905212402344, "resultado": "1.03%", "no_preg\u00f5es": 8}, {"compra_data": "01-02-2019", "compra_pre\u00e7o": 14.757004737854004, "venda_data": "06-02-2019", "venda_pre\u00e7o": 14.31803035736084, "resultado": "-2.97%", "no_preg\u00f5es": 3}, {"compra_data": "13-02-2019", "compra_pre\u00e7o": 14.598227500915527, "venda_data": "15-02-2019", "venda_pre\u00e7o": 14.458127975463867, "resultado": "-0.96%", "no_preg\u00f5es": 2}, {"compra_data": "18-02-2019", "compra_pre\u00e7o": 14.523506164550781, "venda_data": "21-02-2019", "venda_pre\u00e7o": 14.103214263916016, "resultado": "-2.89%", "no_preg\u00f5es": 3}, {"compra_data": "26-02-2019", "compra_pre\u00e7o": 14.458127975463867, "venda_data": "28-02-2019", "venda_pre\u00e7o": 14.140571594238281, "resultado": "-2.20%", "no_preg\u00f5es": 2}, {"compra_data": "13-03-2019", "compra_pre\u00e7o": 14.084847450256348, "venda_data": "14-03-2019", "venda_pre\u00e7o": 13.8779935836792, "resultado": "-1.47%", "no_preg\u00f5es": 1}, {"compra_data": "15-03-2019", "compra_pre\u00e7o": 14.207077980041504, "venda_data": "22-03-2019", "venda_pre\u00e7o": 14.047237396240234, "resultado": "-1.13%", "no_preg\u00f5es": 5}, {"compra_data": "01-04-2019", "compra_pre\u00e7o": 15.11911392211914, "venda_data": "09-04-2019", "venda_pre\u00e7o": 14.667797088623047, "resultado": "-2.99%", "no_preg\u00f5es": 6}, {"compra_data": "08-05-2019", "compra_pre\u00e7o": 13.633530616760254, "venda_data": "09-05-2019", "venda_pre\u00e7o": 13.389066696166992, "resultado": "-1.79%", "no_preg\u00f5es": 1}, {"compra_data": "21-05-2019", "compra_pre\u00e7o": 13.504880905151367, "venda_data": "24-05-2019", "venda_pre\u00e7o": 13.089055061340332, "resultado": "-3.08%", "no_preg\u00f5es": 3}, {"compra_data": "28-05-2019", "compra_pre\u00e7o": 13.363122940063477, "venda_data": "30-05-2019", "venda_pre\u00e7o": 13.183561325073242, "resultado": "-1.34%", "no_preg\u00f5es": 2}, {"compra_data": "07-06-2019", "compra_pre\u00e7o": 13.136307716369629, "venda_data": "02-07-2019", "venda_pre\u00e7o": 13.835651397705078, "resultado": "5.32%", "no_preg\u00f5es": 16}, {"compra_data": "04-07-2019", "compra_pre\u00e7o": 14.459390640258789, "venda_data": "11-07-2019", "venda_pre\u00e7o": 14.119169235229492, "resultado": "-2.35%", "no_preg\u00f5es": 4}, {"compra_data": "30-07-2019", "compra_pre\u00e7o": 13.315868377685547, "venda_data": "31-07-2019", "venda_pre\u00e7o": 12.994548797607422, "resultado": "-2.41%", "no_preg\u00f5es": 1}, {"compra_data": "13-08-2019", "compra_pre\u00e7o": 12.540921211242676, "venda_data": "14-08-2019", "venda_pre\u00e7o": 12.011689186096191, "resultado": "-4.22%", "no_preg\u00f5es": 1}, {"compra_data": "22-08-2019", "compra_pre\u00e7o": 11.983336448669434, "venda_data": "23-08-2019", "venda_pre\u00e7o": 11.679240226745605, "resultado": "-2.54%", "no_preg\u00f5es": 1}, {"compra_data": "29-08-2019", "compra_pre\u00e7o": 11.907312393188477, "venda_data": "06-09-2019", "venda_pre\u00e7o": 11.812281608581543, "resultado": "-0.80%", "no_preg\u00f5es": 6}, {"compra_data": "09-09-2019", "compra_pre\u00e7o": 12.458489418029785, "venda_data": "19-09-2019", "venda_pre\u00e7o": 12.734077453613281, "resultado": "2.21%", "no_preg\u00f5es": 8}, {"compra_data": "04-10-2019", "compra_pre\u00e7o": 12.382464408874512, "venda_data": "07-10-2019", "venda_pre\u00e7o": 12.144887924194336, "resultado": "-1.92%", "no_preg\u00f5es": 1}, {"compra_data": "10-10-2019", "compra_pre\u00e7o": 12.334949493408203, "venda_data": "24-10-2019", "venda_pre\u00e7o": 12.353955268859863, "resultado": "0.15%", "no_preg\u00f5es": 10}, {"compra_data": "30-10-2019", "compra_pre\u00e7o": 12.715072631835938, "venda_data": "09-12-2019", "venda_pre\u00e7o": 16.36907958984375, "resultado": "28.74%", "no_preg\u00f5es": 26}, {"compra_data": "10-12-2019", "compra_pre\u00e7o": 16.835948944091797, "venda_data": "24-01-2020", "venda_pre\u00e7o": 20.647146224975586, "resultado": "22.64%", "no_preg\u00f5es": 29}, {"compra_data": "04-02-2020", "compra_pre\u00e7o": 20.418472290039062, "venda_data": "07-02-2020", "venda_pre\u00e7o": 19.29416847229004, "resultado": "-5.51%", "no_preg\u00f5es": 3}, {"compra_data": "11-02-2020", "compra_pre\u00e7o": 20.094520568847656, "venda_data": "14-02-2020", "venda_pre\u00e7o": 19.53236961364746, "resultado": "-2.80%", "no_preg\u00f5es": 3}, {"compra_data": "25-03-2020", "compra_pre\u00e7o": 10.041234016418457, "venda_data": "01-04-2020", "venda_pre\u00e7o": 9.134467124938965, "resultado": "-9.03%", "no_preg\u00f5es": 5}, {"compra_data": "02-04-2020", "compra_pre\u00e7o": 9.583077430725098, "venda_data": "03-04-2020", "venda_pre\u00e7o": 8.905389785766602, "resultado": "-7.07%", "no_preg\u00f5es": 1}, {"compra_data": "07-04-2020", "compra_pre\u00e7o": 9.850334167480469, "venda_data": "24-04-2020", "venda_pre\u00e7o": 10.432574272155762, "resultado": "5.91%", "no_preg\u00f5es": 11}, {"compra_data": "28-04-2020", "compra_pre\u00e7o": 11.43478775024414, "venda_data": "30-04-2020", "venda_pre\u00e7o": 11.205710411071777, "resultado": "-2.00%", "no_preg\u00f5es": 2}, {"compra_data": "07-05-2020", "compra_pre\u00e7o": 11.88339900970459, "venda_data": "13-05-2020", "venda_pre\u00e7o": 11.100716590881348, "resultado": "-6.59%", "no_preg\u00f5es": 4}, {"compra_data": "21-05-2020", "compra_pre\u00e7o": 11.501602172851562, "venda_data": "22-05-2020", "venda_pre\u00e7o": 11.072083473205566, "resultado": "-3.73%", "no_preg\u00f5es": 1}, {"compra_data": "25-05-2020", "compra_pre\u00e7o": 11.797493934631348, "venda_data": "10-06-2020", "venda_pre\u00e7o": 13.687383651733398, "resultado": "16.02%", "no_preg\u00f5es": 12}, {"compra_data": "16-06-2020", "compra_pre\u00e7o": 14.126449584960938, "venda_data": "26-06-2020", "venda_pre\u00e7o": 14.489156723022461, "resultado": "2.57%", "no_preg\u00f5es": 8}, {"compra_data": "29-06-2020", "compra_pre\u00e7o": 14.975944519042969, "venda_data": "01-07-2020", "venda_pre\u00e7o": 14.77550220489502, "resultado": "-1.34%", "no_preg\u00f5es": 2}, {"compra_data": "02-07-2020", "compra_pre\u00e7o": 15.061850547790527, "venda_data": "21-07-2020", "venda_pre\u00e7o": 15.415010452270508, "resultado": "2.34%", "no_preg\u00f5es": 13}, {"compra_data": "22-07-2020", "compra_pre\u00e7o": 15.978158950805664, "venda_data": "23-07-2020", "venda_pre\u00e7o": 15.644088745117188, "resultado": "-2.09%", "no_preg\u00f5es": 1}, {"compra_data": "24-07-2020", "compra_pre\u00e7o": 16.359954833984375, "venda_data": "07-08-2020", "venda_pre\u00e7o": 16.80856704711914, "resultado": "2.74%", "no_preg\u00f5es": 10}, {"compra_data": "10-08-2020", "compra_pre\u00e7o": 17.428983688354492, "venda_data": "13-08-2020", "venda_pre\u00e7o": 17.047189712524414, "resultado": "-2.19%", "no_preg\u00f5es": 3}, {"compra_data": "18-08-2020", "compra_pre\u00e7o": 18.603008270263672, "venda_data": "27-08-2020", "venda_pre\u00e7o": 18.373929977416992, "resultado": "-1.23%", "no_preg\u00f5es": 7}, {"compra_data": "01-09-2020", "compra_pre\u00e7o": 19.08979606628418, "venda_data": "03-09-2020", "venda_pre\u00e7o": 18.49801254272461, "resultado": "-3.10%", "no_preg\u00f5es": 2}, {"compra_data": "04-09-2020", "compra_pre\u00e7o": 19.013439178466797, "venda_data": "21-09-2020", "venda_pre\u00e7o": 19.65294647216797, "resultado": "3.36%", "no_preg\u00f5es": 10}, {"compra_data": "22-09-2020", "compra_pre\u00e7o": 19.77703094482422, "venda_data": "23-09-2020", "venda_pre\u00e7o": 19.710214614868164, "resultado": "-0.34%", "no_preg\u00f5es": 1}, {"compra_data": "30-09-2020", "compra_pre\u00e7o": 19.8533878326416, "venda_data": "02-10-2020", "venda_pre\u00e7o": 19.662490844726562, "resultado": "-0.96%", "no_preg\u00f5es": 2}, {"compra_data": "05-10-2020", "compra_pre\u00e7o": 20.807878494262695, "venda_data": "28-10-2020", "venda_pre\u00e7o": 21.20876121520996, "resultado": "1.93%", "no_preg\u00f5es": 16}, {"compra_data": "03-11-2020", "compra_pre\u00e7o": 22.125076293945312, "venda_data": "04-11-2020", "venda_pre\u00e7o": 21.266035079956055, "resultado": "-3.88%", "no_preg\u00f5es": 1}, {"compra_data": "17-11-2020", "compra_pre\u00e7o": 20.525962829589844, "venda_data": "18-11-2020", "venda_pre\u00e7o": 20.122926712036133, "resultado": "-1.96%", "no_preg\u00f5es": 1}, {"compra_data": "19-11-2020", "compra_pre\u00e7o": 20.382020950317383, "venda_data": "03-12-2020", "venda_pre\u00e7o": 21.571931838989258, "resultado": "5.84%", "no_preg\u00f5es": 9}, {"compra_data": "04-12-2020", "compra_pre\u00e7o": 22.013351440429688, "venda_data": "09-12-2020", "venda_pre\u00e7o": 21.71587371826172, "resultado": "-1.35%", "no_preg\u00f5es": 3}, {"compra_data": "15-12-2020", "compra_pre\u00e7o": 22.838611602783203, "venda_data": "13-01-2021", "venda_pre\u00e7o": 25.714332580566406, "resultado": "12.59%", "no_preg\u00f5es": 17}, {"compra_data": "14-01-2021", "compra_pre\u00e7o": 26.786972045898438, "venda_data": "15-01-2021", "venda_pre\u00e7o": 25.202171325683594, "resultado": "-5.92%", "no_preg\u00f5es": 1}, {"compra_data": "05-02-2021", "compra_pre\u00e7o": 23.38545036315918, "venda_data": "22-03-2021", "venda_pre\u00e7o": 26.960506439208984, "resultado": "15.29%", "no_preg\u00f5es": 28}, {"compra_data": "26-03-2021", "compra_pre\u00e7o": 27.766311645507812, "venda_data": "30-04-2021", "venda_pre\u00e7o": 32.25164031982422, "resultado": "16.15%", "no_preg\u00f5es": 23}, {"compra_data": "05-05-2021", "compra_pre\u00e7o": 33.44578552246094, "venda_data": "14-05-2021", "venda_pre\u00e7o": 33.60111999511719, "resultado": "0.46%", "no_preg\u00f5es": 7}, {"compra_data": "18-05-2021", "compra_pre\u00e7o": 35.22175216674805, "venda_data": "19-05-2021", "venda_pre\u00e7o": 34.83869552612305, "resultado": "-1.09%", "no_preg\u00f5es": 1}, {"compra_data": "01-06-2021", "compra_pre\u00e7o": 33.51272201538086, "venda_data": "04-06-2021", "venda_pre\u00e7o": 31.882266998291016, "resultado": "-4.87%", "no_preg\u00f5es": 2}, {"compra_data": "11-06-2021", "compra_pre\u00e7o": 32.412654876708984, "venda_data": "14-06-2021", "venda_pre\u00e7o": 31.52867317199707, "resultado": "-2.73%", "no_preg\u00f5es": 1}, {"compra_data": "24-06-2021", "compra_pre\u00e7o": 30.222347259521484, "venda_data": "30-06-2021", "venda_pre\u00e7o": 29.082992553710938, "resultado": "-3.77%", "no_preg\u00f5es": 4}]