[{"compra_data": "30-03-2015", "compra_pre\u00e7o": 5.570162773132324, "venda_data": "27-07-2015", "venda_pre\u00e7o": 6.494253158569336, "resultado": "16.59%", "no_preg\u00f5es": 17}, {"compra_data": "23-11-2015", "compra_pre\u00e7o": 5.45347261428833, "venda_data": "28-12-2015", "venda_pre\u00e7o": 5.226184844970703, "resultado": "-4.17%", "no_preg\u00f5es": 5}, {"compra_data": "26-01-2016", "compra_pre\u00e7o": 5.404468059539795, "venda_data": "01-02-2016", "venda_pre\u00e7o": 5.103832244873047, "resultado": "-5.56%", "no_preg\u00f5es": 1}, {"compra_data": "14-03-2016", "compra_pre\u00e7o": 5.062253952026367, "venda_data": "21-03-2016", "venda_pre\u00e7o": 4.904806137084961, "resultado": "-3.11%", "no_preg\u00f5es": 1}, {"compra_data": "28-03-2016", "compra_pre\u00e7o": 5.053009033203125, "venda_data": "23-05-2016", "venda_pre\u00e7o": 5.151811122894287, "resultado": "1.96%", "no_preg\u00f5es": 8}, {"compra_data": "30-05-2016", "compra_pre\u00e7o": 5.232969284057617, "venda_data": "06-06-2016", "venda_pre\u00e7o": 5.056537628173828, "resultado": "-3.37%", "no_preg\u00f5es": 1}, {"compra_data": "18-07-2016", "compra_pre\u00e7o": 5.198218822479248, "venda_data": "31-10-2016", "venda_pre\u00e7o": 6.05532169342041, "resultado": "16.49%", "no_preg\u00f5es": 15}, {"compra_data": "26-12-2016", "compra_pre\u00e7o": 5.557366847991943, "venda_data": "09-01-2017", "venda_pre\u00e7o": 5.431879043579102, "resultado": "-2.26%", "no_preg\u00f5es": 2}, {"compra_data": "16-01-2017", "compra_pre\u00e7o": 5.535855770111084, "venda_data": "10-04-2017", "venda_pre\u00e7o": 6.058801651000977, "resultado": "9.45%", "no_preg\u00f5es": 12}, {"compra_data": "24-04-2017", "compra_pre\u00e7o": 6.394800186157227, "venda_data": "12-06-2017", "venda_pre\u00e7o": 6.535703659057617, "resultado": "2.20%", "no_preg\u00f5es": 7}, {"compra_data": "10-07-2017", "compra_pre\u00e7o": 6.888053894042969, "venda_data": "23-10-2017", "venda_pre\u00e7o": 7.869997978210449, "resultado": "14.26%", "no_preg\u00f5es": 15}, {"compra_data": "13-11-2017", "compra_pre\u00e7o": 8.136096954345703, "venda_data": "29-01-2018", "venda_pre\u00e7o": 8.312942504882812, "resultado": "2.17%", "no_preg\u00f5es": 11}, {"compra_data": "16-04-2018", "compra_pre\u00e7o": 8.420405387878418, "venda_data": "30-04-2018", "venda_pre\u00e7o": 8.218256950378418, "resultado": "-2.40%", "no_preg\u00f5es": 2}, {"compra_data": "07-05-2018", "compra_pre\u00e7o": 8.500164031982422, "venda_data": "28-05-2018", "venda_pre\u00e7o": 8.146586418151855, "resultado": "-4.16%", "no_preg\u00f5es": 3}, {"compra_data": "10-07-2018", "compra_pre\u00e7o": 8.214171409606934, "venda_data": "08-10-2018", "venda_pre\u00e7o": 8.884358406066895, "resultado": "8.16%", "no_preg\u00f5es": 13}, {"compra_data": "02-01-2019", "compra_pre\u00e7o": 17.020479202270508, "venda_data": "07-01-2019", "venda_pre\u00e7o": 9.036486625671387, "resultado": "-46.91%", "no_preg\u00f5es": 1}, {"compra_data": "11-03-2019", "compra_pre\u00e7o": 9.352781295776367, "venda_data": "18-03-2019", "venda_pre\u00e7o": 8.847748756408691, "resultado": "-5.40%", "no_preg\u00f5es": 1}, {"compra_data": "01-04-2019", "compra_pre\u00e7o": 9.28416633605957, "venda_data": "08-04-2019", "venda_pre\u00e7o": 8.880083084106445, "resultado": "-4.35%", "no_preg\u00f5es": 1}, {"compra_data": "15-04-2019", "compra_pre\u00e7o": 9.069953918457031, "venda_data": "06-05-2019", "venda_pre\u00e7o": 8.972583770751953, "resultado": "-1.07%", "no_preg\u00f5es": 3}, {"compra_data": "27-05-2019", "compra_pre\u00e7o": 9.27442741394043, "venda_data": "19-08-2019", "venda_pre\u00e7o": 10.880995750427246, "resultado": "17.32%", "no_preg\u00f5es": 12}, {"compra_data": "09-09-2019", "compra_pre\u00e7o": 11.6155366897583, "venda_data": "09-03-2020", "venda_pre\u00e7o": 17.013952255249023, "resultado": "46.48%", "no_preg\u00f5es": 26}, {"compra_data": "20-04-2020", "compra_pre\u00e7o": 19.09139633178711, "venda_data": "11-05-2020", "venda_pre\u00e7o": 17.95705795288086, "resultado": "-5.94%", "no_preg\u00f5es": 3}, {"compra_data": "25-05-2020", "compra_pre\u00e7o": 20.630151748657227, "venda_data": "31-08-2020", "venda_pre\u00e7o": 31.890806198120117, "resultado": "54.58%", "no_preg\u00f5es": 14}, {"compra_data": "28-09-2020", "compra_pre\u00e7o": 33.17454528808594, "venda_data": "23-11-2020", "venda_pre\u00e7o": 38.0975341796875, "resultado": "14.84%", "no_preg\u00f5es": 8}, {"compra_data": "04-01-2021", "compra_pre\u00e7o": 44.44322967529297, "venda_data": "18-02-2021", "venda_pre\u00e7o": 41.205772399902344, "resultado": "-7.28%", "no_preg\u00f5es": 6}, {"compra_data": "12-04-2021", "compra_pre\u00e7o": 38.330894470214844, "venda_data": "26-04-2021", "venda_pre\u00e7o": 34.83360290527344, "resultado": "-9.12%", "no_preg\u00f5es": 2}, {"compra_data": "14-06-2021", "compra_pre\u00e7o": 35.0126953125, "venda_data": "21-06-2021", "venda_pre\u00e7o": 33.39091110229492, "resultado": "-4.63%", "no_preg\u00f5es": 1}]